this_system/__init__.py
this_system/__version__.py
this_system/browser.py
this_system/network.py
this_system/platform.py
this_system/python.py
this_system/system.py
this_system-0.1.0.dist-info/LICENSE
this_system-0.1.0.dist-info/METADATA
this_system-0.1.0.dist-info/WHEEL
this_system-0.1.0.dist-info/RECORD
