Metadata-Version: 2.1
Name: this_system
Version: 0.1.0
Summary: 
Home-page: https://gitlab.com/Anonym0u5/this_system
License: GPL-3.0-or-later
Author: an0nym0u5
Author-email: anonym0u5@disroot.org
Requires-Python: >=3.11,<4.0
Classifier: Development Status :: 3 - Alpha
Classifier: Environment :: Other Environment
Classifier: Intended Audience :: Developers
Classifier: License :: OSI Approved :: GNU General Public License v3 or later (GPLv3+)
Classifier: Natural Language :: English
Classifier: Operating System :: OS Independent
Classifier: Programming Language :: Python :: 3
Classifier: Programming Language :: Python :: 3.11
Classifier: Programming Language :: Python :: 3.12
Classifier: Topic :: Software Development
Classifier: Topic :: Software Development :: Libraries
Classifier: Topic :: Software Development :: Libraries :: Python Modules
Requires-Dist: psutil (>=5.9.8,<6.0.0)
Requires-Dist: pyxdg (>=0.28,<0.29)
Project-URL: Documentation, https://this_system.readthedocs.io
Project-URL: Repository, https://gitlab.com/Anonym0u5/this_system.git
